behavior_machine/__init__.py
behavior_machine/core/__init__.py
behavior_machine/core/board.py
behavior_machine/core/machine.py
behavior_machine/core/nested_state.py
behavior_machine/core/state.py
behavior_machine/core/state_status.py
behavior_machine/core/utils.py
behavior_machine/library/__init__.py
behavior_machine/library/atleastone_state.py
behavior_machine/library/common_state.py
behavior_machine/library/parallel_state.py
behavior_machine/library/print_state.py
behavior_machine/library/probability_states.py
behavior_machine/library/selector_state.py
behavior_machine/library/sequential_state.py
behavior_machine/visualization/__init__.py
behavior_machine/visualization/visualize.py
tests/__init__.py
tests/board_test.py
tests/performance_test.py
tests/standard_state_test.py
tests/state_test.py
tests/statemachine_test.py
tests/library/__init__.py
tests/library/access_flow_state_test.py
tests/library/atleastone_state_test.py
tests/library/parallel_state_test.py
tests/library/prob_states_test.py
tests/library/selector_state_test.py
tests/library/sequential_state_test.py
tests/library/set_get_board_state_test.py
behavior_machine-0.4.0.dist-info/LICENSE
behavior_machine-0.4.0.dist-info/METADATA
behavior_machine-0.4.0.dist-info/WHEEL
behavior_machine-0.4.0.dist-info/top_level.txt
behavior_machine-0.4.0.dist-info/RECORD
