Metadata-Version: 2.1
Name: behavior-machine
Version: 0.4.0
Summary: An implementation of a behavior tree + hierarchical state machine hybrid.
Home-page: https://github.com/CMU-TBD/behavior_machine
Author: Xiang Zhi Tan
Author-email: zhi.tan@ri.cmu.edu
License: MIT
Platform: UNKNOWN
Requires-Python: >=3.6
